more_snowpark/__init__.py
more_snowpark/config.py
more_snowpark/dataframe.py
more_snowpark/session.py
more_snowpark-0.0.1.dist-info/LICENSE
more_snowpark-0.0.1.dist-info/METADATA
more_snowpark-0.0.1.dist-info/WHEEL
more_snowpark-0.0.1.dist-info/RECORD
